ssave/__cui__.py
ssave/__init__.py
ssave-1.0.6.dist-info/METADATA
ssave-1.0.6.dist-info/WHEEL
ssave-1.0.6.dist-info/top_level.txt
ssave-1.0.6.dist-info/RECORD
