Metadata-Version: 2.1
Name: ssave
Version: 1.0.6
Summary: SCOS Save Utility for Python3
Home-page: https://github.com/SCOS-Apps/Save-Utility
Author: SCOS-Apps
Author-email: hsc100zz@gmail.com
